README.md
setup.py
tests/__init__.py
w2re/__init__.py
w2re/command_line_w2re.py
w2re/formatters.py
w2re/utils.py
w2re.egg-info/PKG-INFO
w2re.egg-info/SOURCES.txt
w2re.egg-info/dependency_links.txt
w2re.egg-info/entry_points.txt
w2re.egg-info/top_level.txt
w2re/prefix_tree/__init__.py
w2re/prefix_tree/letter_range_utils.py
w2re/prefix_tree/primitives.py
w2re/prefix_tree/tree.py